edahub/__init__.py
edahub/logic/__init__.py
edahub/logic/pandas_csv.py
edahub/logic/project.py
edahub/logic/stats_calculator.py
edahub/logic/vis/__init__.py
edahub/logic/vis/binning.py
edahub/logic/vis/histogram.py
edahub/widgets/__init__.py
edahub/widgets/column_summary.py
edahub/widgets/custom.py
edahub/widgets/main.py
edahub-0.0.3.dist-info/METADATA
edahub-0.0.3.dist-info/WHEEL
edahub-0.0.3.dist-info/top_level.txt
edahub-0.0.3.dist-info/RECORD
