Metadata-Version: 2.1
Name: edahub
Version: 0.0.3
Summary: EDAHub helps structure exploratory data analysis (EDA) results.
Home-page: https://github.com/not-so-fat/edahub
Author: @not-so-fat
Author-email: conjurer.not.so.fat@gmail.com
License: UNKNOWN
Platform: UNKNOWN
Classifier: Programming Language :: Python :: 3
Classifier: License :: OSI Approved :: MIT License
Classifier: Operating System :: OS Independent
Requires-Python: >=3.9
Requires-Dist: altair
Requires-Dist: ipywidgets
Requires-Dist: jupyterlab
Requires-Dist: jupyterlab-widgets
Requires-Dist: pandas
Requires-Dist: sidecar
